Metadata-Version: 2.1
Name: sqlalchemy-sotero
Version: 0.0.3
Summary: Python SQLAlchemy Dialect for Sotero JDBC driver.
Home-page: https://soterosoft.com
Author: Masha Loianych
Author-email: masha@soterosoft.com
License: UNKNOWN
Keywords: Sotero SQLAlchemy JDBC Dialect
Platform: UNKNOWN
Classifier: License :: OSI Approved :: Apache Software License
Classifier: Development Status :: 2 - Pre-Alpha
Classifier: Intended Audience :: Developers
Classifier: Programming Language :: Python
Classifier: Programming Language :: Python :: 3
Classifier: Programming Language :: Python :: Implementation :: CPython
Classifier: Operating System :: OS Independent
Requires-Python: >=3.6
License-File: LICENSE
